consent_decoder/__init__.py
consent_decoder/run.py
consent_decoder/decoder/VendorConsentDecoder.py
consent_decoder/decoder/__init__.py
consent_decoder/util/Bits.py
consent_decoder/util/GdprConstants.py
consent_decoder/util/Purpose.py
consent_decoder/util/__init__.py
consent_decoder/vendor/Vendor.py
consent_decoder/vendor/VendorConsent.py
consent_decoder/vendor/__init__.py
consent_decoder-1.0.1.dist-info/METADATA
consent_decoder-1.0.1.dist-info/RECORD
consent_decoder-1.0.1.dist-info/WHEEL
consent_decoder-1.0.1.dist-info/top_level.txt
