Metadata-Version: 2.1
Name: consent-decoder
Version: 1.0.1
Summary: Decode web-safe base64 consent informationwith the IAB EU's GDPR Transparency and Consent Framework
Home-page: UNKNOWN
Author: Saurav Omar
Author-email: sauravomar@mediaiqdigital.com
License: MediaIQ
Platform: UNKNOWN
